<lootitems>
	<item rate="3521">2020000</item>
	<item rate="167">100089</item>
	<item rate="2476">2020001</item>
	<item rate="521">9406</item>
	<item rate="143">570272</item>
	<item rate="845">9402</item>
	<item rate="233">300128</item>
	<item rate="44">1700072</item>
	<item rate="44">570552</item>
	<item rate="216">1700045</item>
	<item rate="81">200117</item>
	<item rate="163">500109</item>
	<item rate="173">400079</item>
	<item rate="279">51500003</item>
	<item rate="63">800173</item>
	<item rate="171">9407</item>
	<item rate="14">3012072</item>
</lootitems>